tangata/__init__.py
tangata/tangata.py
tangata/tangata_api.py
tangata/tangata_catalog_compile.py
tangata/build/asset-manifest.json
tangata/build/favicon.ico
tangata/build/logo192.png
tangata/build/logo512.png
tangata/build/manifest.json
tangata/build/robots.txt
tangata/static/css/2.108bfca2.chunk.css
tangata/static/css/2.108bfca2.chunk.css.map
tangata/static/css/2.160aed42.chunk.css
tangata/static/css/2.160aed42.chunk.css.map
tangata/static/css/2.6ccd0d06.chunk.css
tangata/static/css/2.6ccd0d06.chunk.css.map
tangata/static/css/2.f7053b59.chunk.css
tangata/static/css/2.f7053b59.chunk.css.map
tangata/static/css/main.03cb636f.chunk.css
tangata/static/css/main.03cb636f.chunk.css.map
tangata/static/css/main.0b94cd05.chunk.css
tangata/static/css/main.0b94cd05.chunk.css.map
tangata/static/css/main.7a0d9bab.chunk.css
tangata/static/css/main.7a0d9bab.chunk.css.map
tangata/static/css/main.7ad8d6fd.chunk.css
tangata/static/css/main.7ad8d6fd.chunk.css.map
tangata/static/css/main.832ff0f6.chunk.css
tangata/static/css/main.832ff0f6.chunk.css.map
tangata/static/css/main.a7c84bc2.chunk.css
tangata/static/css/main.a7c84bc2.chunk.css.map
tangata/static/css/main.b99474c9.chunk.css
tangata/static/css/main.b99474c9.chunk.css.map
tangata/static/css/main.e7c3d6b5.chunk.css
tangata/static/css/main.e7c3d6b5.chunk.css.map
tangata/static/css/main.e9b12610.chunk.css
tangata/static/css/main.e9b12610.chunk.css.map
tangata/static/css/main.f2d62c73.chunk.css
tangata/static/css/main.f2d62c73.chunk.css.map
tangata/static/css/main.fffd18b2.chunk.css
tangata/static/css/main.fffd18b2.chunk.css.map
tangata/static/js/2.04189c92.chunk.js
tangata/static/js/2.04189c92.chunk.js.LICENSE.txt
tangata/static/js/2.04189c92.chunk.js.map
tangata/static/js/2.32732a7b.chunk.js
tangata/static/js/2.32732a7b.chunk.js.LICENSE.txt
tangata/static/js/2.32732a7b.chunk.js.map
tangata/static/js/2.33ecba27.chunk.js
tangata/static/js/2.33ecba27.chunk.js.LICENSE.txt
tangata/static/js/2.33ecba27.chunk.js.map
tangata-0.2.1.dist-info/LICENSE
tangata-0.2.1.dist-info/METADATA
tangata-0.2.1.dist-info/WHEEL
tangata-0.2.1.dist-info/entry_points.txt
tangata-0.2.1.dist-info/top_level.txt
tangata-0.2.1.dist-info/RECORD
