Metadata-Version: 2.1
Name: tangata
Version: 0.2.1
Summary: An interactive catalog for dbt_
Home-page: https://github.com/ciejer/tangata_local
Author: Chris Jenkins
Author-email: chris@chrisjenkins.nz
License: UNKNOWN
Platform: UNKNOWN
Classifier: Programming Language :: Python :: 3
Classifier: License :: OSI Approved :: Apache Software License
Classifier: Operating System :: OS Independent
Classifier: Topic :: Database :: Front-Ends
Classifier: Framework :: Flask
Classifier: Development Status :: 4 - Beta
License-File: LICENSE
Requires-Dist: simple-websocket (==0.2.0)
Requires-Dist: Flask (==1.1.2)
Requires-Dist: Flask-SocketIO (==5.0.3)
Requires-Dist: Whoosh (==2.7.4)
Requires-Dist: APScheduler (==3.7.0)
Requires-Dist: GitPython (==3.1.18)
Requires-Dist: python-dateutil (==2.8.1)
Requires-Dist: PyYAML (==5.4.1)
Requires-Dist: ruamel.base (==1.0.0)
